zpimp/__init__.py
zpimp/importer.py
zpimp-0.1.9.dist-info/licenses/LICENSE
zpimp-0.1.9.dist-info/METADATA
zpimp-0.1.9.dist-info/WHEEL
zpimp-0.1.9.dist-info/top_level.txt
zpimp-0.1.9.dist-info/RECORD
