Metadata-Version: 2.4
Name: zpimp
Version: 0.1.9
Summary: Library for importing and executing Python Code from Apache Zeppelin notes inside other notes
Author-email: Ilia Semenov <semenov_ilya_01@mail.ru>
License:                                  Apache License
Keywords: zeppelin,note,import,python,apache
Classifier: Development Status :: 3 - Alpha
Classifier: Intended Audience :: Developers
Classifier: Topic :: Software Development :: Libraries :: Python Modules
Classifier: License :: OSI Approved :: Apache Software License
Classifier: Programming Language :: Python :: 3
Classifier: Programming Language :: Python :: 3.7
Classifier: Programming Language :: Python :: 3.8
Classifier: Programming Language :: Python :: 3.9
Classifier: Programming Language :: Python :: 3.10
Classifier: Programming Language :: Python :: 3.11
Classifier: Operating System :: OS Independent
Requires-Python: >=3.7
License-File: LICENSE
Dynamic: license-file
